odoo/addons/shopinvader_product_attribute_set/README.rst
odoo/addons/shopinvader_product_attribute_set/__init__.py
odoo/addons/shopinvader_product_attribute_set/__manifest__.py
odoo/addons/shopinvader_product_attribute_set/i18n/shopinvader_product_attribute_set.pot
odoo/addons/shopinvader_product_attribute_set/models/__init__.py
odoo/addons/shopinvader_product_attribute_set/models/attribute_attribute.py
odoo/addons/shopinvader_product_attribute_set/readme/CONTRIBUTORS.rst
odoo/addons/shopinvader_product_attribute_set/readme/DESCRIPTION.rst
odoo/addons/shopinvader_product_attribute_set/schemas/__init__.py
odoo/addons/shopinvader_product_attribute_set/schemas/product.py
odoo/addons/shopinvader_product_attribute_set/schemas/product_attribute.py
odoo/addons/shopinvader_product_attribute_set/schemas/product_attribute_group.py
odoo/addons/shopinvader_product_attribute_set/schemas/product_attribute_set.py
odoo/addons/shopinvader_product_attribute_set/static/description/index.html
odoo/addons/shopinvader_product_attribute_set/tests/__init__.py
odoo/addons/shopinvader_product_attribute_set/tests/test_product.py
odoo_addon_shopinvader_product_attribute_set-16.0.1.0.2.dist-info/METADATA
odoo_addon_shopinvader_product_attribute_set-16.0.1.0.2.dist-info/WHEEL
odoo_addon_shopinvader_product_attribute_set-16.0.1.0.2.dist-info/top_level.txt
odoo_addon_shopinvader_product_attribute_set-16.0.1.0.2.dist-info/RECORD
