Metadata-Version: 2.1
Name: odoo-addon-shopinvader-product-attribute-set
Version: 16.0.1.0.2
Summary: Expose all PIM' Attribute sets with Shopinvader
Home-page: https://github.com/shopinvader/odoo-shopinvader
Author: Akretion
License: AGPL-3
Platform: UNKNOWN
Classifier: Programming Language :: Python
Classifier: Framework :: Odoo
Classifier: Framework :: Odoo :: 16.0
Classifier: License :: OSI Approved :: GNU Affero General Public License v3
Requires-Python: >=3.10
Requires-Dist: odoo-addon-product-attribute-set <16.1dev,>=16.0dev
Requires-Dist: odoo-addon-shopinvader-product <16.1dev,>=16.0dev
Requires-Dist: odoo <16.1dev,>=16.0a
